{
  "list": {
    "Enma Infini": [
      "yokai",
      0.01626
    ],
    "Enma l'Ancien": [
      "yokai",
      0.01626
    ],
    "Enma funèbre": [
      "yokai",
      0.01626
    ],
    "Enma Solaire": [
      "yokai",
      0.01626
    ],
    "Zazel le Bon": [
      "yokai",
      0.01626
    ],
    "Domniscian 2.0": [
      "yokai",
      0.01626
    ],
    "Camélia": [
      "yokai",
      0.03252
    ],
    "Robonyan F": [
      "yokai",
      0.03252
    ],
    "Nunchucky": [
      "yokai",
      0.03252
    ],
    "Scarnage": [
      "yokai",
      0.03252
    ],
    "Blanche Hase": [
      "yokai",
      0.03252
    ],
    "Barakabo": [
      "yokai",
      0.03252
    ],
    "El Squalador": [
      "yokai",
      0.03252
    ],
    "Oronyan": [
      "yokai",
      0.03252
    ],
    "Bambinflammable": [
      "yokai",
      0.03252
    ],
    "Damona": [
      "yokai",
      0.03252
    ],
    "Supervolt": [
      "yokai",
      0.03252
    ],
    "Tata Câlin": [
      "yokai",
      0.03252
    ],
    "Dr Crépuscule": [
      "yokai",
      0.03252
    ],
    "Dente": [
      "yokai",
      0.03252
    ],
    "Horridjinn": [
      "yokai",
      0.03252
    ],
    "Éterna": [
      "yokai",
      0.03252
    ],
    "Godichezilla": [
      "yokai",
      0.03252
    ],
    "Octorgombre": [
      "yokai",
      0.03252
    ],
    "Komak": [
      "yokai",
      0.00813
    ],
    "Jiganyan": [
      "yokai",
      0.00813
    ],
    "Grolos": [
      "yokai",
      0.00813
    ],
    "Flûte enchantée": [
      "obj",
      0.04878
    ],
    "Épée Enma": [
      "obj",
      0.04878
    ],
    "Épée émoussée": [
      "obj",
      0.03252
    ],
    "Bannière seigneur": [
      "obj",
      0.03252
    ],
    "Sac tourbillonannt": [
      "obj",
      0.03252
    ],
    "Paille glamour": [
      "obj",
      0.03252
    ],
    "Trésor du feu": [
      "treasure",
      0.03252
    ],
    "Trésor du soleil": [
      "treasure",
      0.03252
    ]
  }
}